normalization_gan/__init__.py
normalization_gan/normalization.py
normalization_gan-0.0.4.dist-info/METADATA
normalization_gan-0.0.4.dist-info/WHEEL
normalization_gan-0.0.4.dist-info/top_level.txt
normalization_gan-0.0.4.dist-info/RECORD
