Metadata-Version: 2.1
Name: normalization-gan
Version: 0.0.4
Summary: Normalization for TTS Input
Author: Aruj Deshwal
Author-email: aruj@gan.studio
Keywords: python
Classifier: Development Status :: 3 - Alpha
Classifier: Intended Audience :: Education
Classifier: Programming Language :: Python :: 3
Classifier: Operating System :: MacOS :: MacOS X
Classifier: Operating System :: Microsoft :: Windows
Requires-Dist: openai
